{
    "sourceFile": "frontend/app/dashboard/(routes)/patients/layout.tsx",
    "activeCommit": 0,
    "commits": [
        {
            "activePatchIndex": 4,
            "patches": [
                {
                    "date": 1738502751148,
                    "content": "Index: \n===================================================================\n--- \n+++ \n"
                },
                {
                    "date": 1738512339618,
                    "content": "Index: \n===================================================================\n--- \n+++ \n@@ -1,7 +1,7 @@\n import { DashboardProvider } from \"@/components/context/Dashboardprovider\";\r\n import BreadCrumb from \"@/components/doctorProfile/BreadCrumb\";\r\n-const RootLayout = async ({ children }: { children: React.ReactNode }) => {\r\n+const RootLayout =  ({ children }: { children: React.ReactNode }) => {\r\n   return (\r\n     <DashboardProvider>\r\n       <main className=\"h-screen flex flex-col pt-14 px-4 overflow-y-scroll lg:overflow-hidden\">\r\n         <BreadCrumb />\r\n"
                },
                {
                    "date": 1738512348044,
                    "content": "Index: \n===================================================================\n--- \n+++ \n@@ -1,6 +1,9 @@\n import { DashboardProvider } from \"@/components/context/Dashboardprovider\";\r\n import BreadCrumb from \"@/components/doctorProfile/BreadCrumb\";\r\n+\r\n+\r\n+export const metadata:Meta\r\n const RootLayout =  ({ children }: { children: React.ReactNode }) => {\r\n   return (\r\n     <DashboardProvider>\r\n       <main className=\"h-screen flex flex-col pt-14 px-4 overflow-y-scroll lg:overflow-hidden\">\r\n"
                },
                {
                    "date": 1738512353721,
                    "content": "Index: \n===================================================================\n--- \n+++ \n@@ -1,9 +1,12 @@\n import { DashboardProvider } from \"@/components/context/Dashboardprovider\";\r\n import BreadCrumb from \"@/components/doctorProfile/BreadCrumb\";\r\n+import { Metadata } from \"next\";\r\n \r\n \r\n-export const metadata:Meta\r\n+export const metadata:Metadata = {\r\n+  tot\r\n+}\r\n const RootLayout =  ({ children }: { children: React.ReactNode }) => {\r\n   return (\r\n     <DashboardProvider>\r\n       <main className=\"h-screen flex flex-col pt-14 px-4 overflow-y-scroll lg:overflow-hidden\">\r\n"
                },
                {
                    "date": 1738512365914,
                    "content": "Index: \n===================================================================\n--- \n+++ \n@@ -3,9 +3,9 @@\n import { Metadata } from \"next\";\r\n \r\n \r\n export const metadata:Metadata = {\r\n-  title:\"Dashboard - Pati\"\r\n+  title:\"Dashboard - Patients\"\r\n }\r\n const RootLayout =  ({ children }: { children: React.ReactNode }) => {\r\n   return (\r\n     <DashboardProvider>\r\n"
                }
            ],
            "date": 1738502751148,
            "name": "Commit-0",
            "content": "import { DashboardProvider } from \"@/components/context/Dashboardprovider\";\r\nimport BreadCrumb from \"@/components/doctorProfile/BreadCrumb\";\r\nconst RootLayout = async ({ children }: { children: React.ReactNode }) => {\r\n  return (\r\n    <DashboardProvider>\r\n      <main className=\"h-screen flex flex-col pt-14 px-4 overflow-y-scroll lg:overflow-hidden\">\r\n        <BreadCrumb />\r\n        {children}\r\n      </main>\r\n    </DashboardProvider>\r\n  );\r\n};\r\n\r\nexport default RootLayout;\r\n"
        }
    ]
}